{
  "upstream_head": "8a362e9e",
  "upstream_subject": "fix mute bug (#1760)",
  "upstream_date": "2026-07-22T17:03:01+08:00",
  "latest_tag": "v0.9.4",
  "merge_base": "cdbc2239",
  "behind": 17,
  "trial_clean": false,
  "conflicts": [
    ".nix/bun-lock-hash",
    "package.json",
    "scripts/gen_catalog.py",
    "src-tauri/Cargo.toml",
    "src-tauri/src/handy/managers/transcription.rs",
    "src/components/Sidebar.tsx",
    "src/components/settings/AccelerationSelector.tsx"
  ],
  "drift": [],
  "checked_at": "2026-07-23T01:19:48Z"
}